flux_proxy/__init__.py
flux_proxy/auth.py
flux_proxy/dispatcher.py
flux_proxy/exceptions.py
flux_proxy/helpers.py
flux_proxy/log.py
flux_proxy/messages.py
flux_proxy/protocol.py
flux_proxy/protocol_jsonrpc.py
flux_proxy/rpc_client.py
flux_proxy/rpc_server.py
flux_proxy/symbols.py
flux_proxy/transport/client_transport.py
flux_proxy/transport/server_transport.py
flux_proxy/tunnel_client.py
flux_proxy-0.2.4.dist-info/METADATA
flux_proxy-0.2.4.dist-info/WHEEL
flux_proxy-0.2.4.dist-info/RECORD
