Metadata-Version: 2.1
Name: flux-proxy
Version: 0.2.4
Summary: A proxy to connect to Flux Configure Frontend
License: AGPL
Author: David White
Author-email: david@runonflux.io
Requires-Python: >=3.12,<4.0
Classifier: License :: Other/Proprietary License
Classifier: Programming Language :: Python :: 3
Classifier: Programming Language :: Python :: 3.12
Requires-Dist: aiofiles (>=24.1.0,<25.0.0)
Requires-Dist: aiohttp (>=3.10.5,<4.0.0)
Requires-Dist: dnspython (>=2.6.1,<3.0.0)
Requires-Dist: pycryptodomex (>=3.20.0,<4.0.0)
Requires-Dist: pymongo (>=4.8.0,<5.0.0)
Requires-Dist: python-bitcoinlib (>=0.12.2,<0.13.0)
Requires-Dist: rich (>=13.7.1,<14.0.0)
